README.md
setup.py
cvlab/__init__.py
cvlab/__main__.py
cvlab/version.py
cvlab.egg-info/PKG-INFO
cvlab.egg-info/SOURCES.txt
cvlab.egg-info/dependency_links.txt
cvlab.egg-info/entry_points.txt
cvlab.egg-info/requires.txt
cvlab.egg-info/top_level.txt
cvlab/core/__init__.py
cvlab/core/core_element.py
cvlab/core/exceptions.py
cvlab/core/hooks.py
cvlab/core/processing_time.py
cvlab/core/threaded_element.py
cvlab/core/update.py
cvlab/diagram/__init__.py
cvlab/diagram/code_generator.py
cvlab/diagram/connectors.py
cvlab/diagram/data.py
cvlab/diagram/diagram.py
cvlab/diagram/element.py
cvlab/diagram/errors.py
cvlab/diagram/id_manager.py
cvlab/diagram/interface.py
cvlab/diagram/parameters.py
cvlab/diagram/serialization.py
cvlab/diagram/elements/__init__.py
cvlab/diagram/elements/affine.py
cvlab/diagram/elements/base.py
cvlab/diagram/elements/basic_transforms.py
cvlab/diagram/elements/blur.py
cvlab/diagram/elements/code.py
cvlab/diagram/elements/color.py
cvlab/diagram/elements/comment.py
cvlab/diagram/elements/data_flow.py
cvlab/diagram/elements/data_generation.py
cvlab/diagram/elements/data_types.py
cvlab/diagram/elements/edges.py
cvlab/diagram/elements/filters.py
cvlab/diagram/elements/image_generation.py
cvlab/diagram/elements/image_io.py
cvlab/diagram/elements/operators.py
cvlab/diagram/elements/presentation.py
cvlab/diagram/elements/segmentation.py
cvlab/diagram/elements/video.py
cvlab/diagram/elements/video_io.py
cvlab/images/default.png
cvlab/images/default.svg
cvlab/images/fractal.avi
cvlab/images/icon-mini.png
cvlab/images/icon.png
cvlab/images/icon.svg
cvlab/images/icon128.png
cvlab/images/icon256.png
cvlab/images/icon64.png
cvlab/images/lena.jpg
cvlab/images/splash.png
cvlab/styles/fonts/Carlito-Bold.ttf
cvlab/styles/fonts/Carlito-BoldItalic.ttf
cvlab/styles/fonts/Carlito-Italic.ttf
cvlab/styles/fonts/Carlito-Regular.ttf
cvlab/styles/themes/common.stylesheet
cvlab/styles/themes/highdpi.stylesheet
cvlab/styles/themes/dark/background-highdpi.png
cvlab/styles/themes/dark/background.png
cvlab/styles/themes/dark/dark.stylesheet
cvlab/styles/themes/dark/down.png
cvlab/styles/themes/dark/up.png
