Metadata-Version: 2.1
Name: cvlab
Version: 1.3.0
Summary: CV Lab - Computer Vision Laboratory - a rapid prototyping tool for computer vision algorithms
Home-page: https://github.com/cvlab-ai/cvlab
Author: Adam Brzeski, Jan Cychnerski
Author-email: adam.m.brzeski@gmail.com, jan.cychnerski@gmail.com
License: AGPL-3.0+
Platform: UNKNOWN
Classifier: Development Status :: 5 - Production/Stable
Classifier: Intended Audience :: Science/Research
Classifier: Intended Audience :: Developers
Classifier: Intended Audience :: Education
Classifier: License :: OSI Approved :: GNU Affero General Public License v3 or later (AGPLv3+)
Classifier: Natural Language :: English
Classifier: Operating System :: OS Independent
Classifier: Programming Language :: Python :: 3
Classifier: Topic :: Scientific/Engineering :: Image Recognition
Classifier: Topic :: Scientific/Engineering :: Visualization
Classifier: Topic :: Scientific/Engineering :: Artificial Intelligence
Classifier: Topic :: Software Development :: Code Generators
Requires-Python: >=3.3
